python_lsp_autoimport/__about__.py
python_lsp_autoimport/__init__.py
python_lsp_autoimport/plugin.py
python_lsp_autoimport-0.0.1.dist-info/entry_points.txt
python_lsp_autoimport-0.0.1.dist-info/LICENSE
python_lsp_autoimport-0.0.1.dist-info/WHEEL
python_lsp_autoimport-0.0.1.dist-info/METADATA
python_lsp_autoimport-0.0.1.dist-info/RECORD
