Metadata-Version: 2.1
Name: python-lsp-autoimport
Version: 0.0.1
Summary: Python LSP auto import plugin
Home-page: https://github.com/frbor/python-lsp-autoimport
License: MIT
Author: Fredrik Borg
Author-email: fredrikb.borg@gmail.com
Requires-Python: >=3.6.2,<4.0.0
Classifier: License :: OSI Approved :: MIT License
Classifier: Operating System :: OS Independent
Classifier: Programming Language :: Python :: 3
Classifier: Programming Language :: Python :: 3.7
Classifier: Programming Language :: Python :: 3.8
Classifier: Programming Language :: Python :: 3.9
Classifier: Programming Language :: Python :: 3.10
Classifier: Programming Language :: Python :: 3
Requires-Dist: autoimport
Requires-Dist: isort (>=5.10.0)
Requires-Dist: python-lsp-server
